retryloop/README.MD
retryloop/__init__.py
retryloop/requirements.txt
retryloop/thirdparty.json
retryloop-0.10.dist-info/LICENSE.rst
retryloop-0.10.dist-info/METADATA
retryloop-0.10.dist-info/WHEEL
retryloop-0.10.dist-info/top_level.txt
retryloop-0.10.dist-info/RECORD
