Metadata-Version: 2.1
Name: retryloop
Version: 0.10
Summary: allows you to execute a given function on each element of an iterable, with the ability to retry failed attempts a specified number of times
Home-page: https://github.com/hansalemaos/retryloop
Author: Johannes Fischer
Author-email: aulasparticularesdealemaosp@gmail.com
License: MIT
Keywords: retry,loop
Classifier: Development Status :: 4 - Beta
Classifier: Programming Language :: Python :: 3 :: Only
Classifier: Programming Language :: Python :: 3.10
Classifier: Topic :: Software Development :: Libraries :: Python Modules
Classifier: Topic :: Utilities
License-File: LICENSE.rst
